flask_login_role/__init__.py
flask_login_role/role_required.py
Flask_Login_Role-1.0.0.dist-info/METADATA
Flask_Login_Role-1.0.0.dist-info/WHEEL
Flask_Login_Role-1.0.0.dist-info/top_level.txt
Flask_Login_Role-1.0.0.dist-info/RECORD
