Metadata-Version: 2.1
Name: Flask-Login-Role
Version: 1.0.0
Summary: A super light-weight alternative to Flask-User or Flask-Security that adds role requirements for views to Flask-Login.
Author: glyzinieh
Author-email: wisteriatp@gmail.com
Requires-Dist: flask
Requires-Dist: flask-login
